README.rst
setup.py
bin/selfcontain
selfcontain/__init__.py
selfcontain/selfcontain.py
selfcontain.egg-info/PKG-INFO
selfcontain.egg-info/SOURCES.txt
selfcontain.egg-info/dependency_links.txt
selfcontain.egg-info/requires.txt
selfcontain.egg-info/top_level.txt