Metadata-Version: 1.1
Name: selfcontain
Version: 0.2
Summary: shoe-horn a web page into a single html file
Home-page: https://github.com/ajschumacher/selfcontain
Author: Aaron Schumacher
Author-email: ajschumacher@gmail.com
License: MIT
Download-URL: https://github.com/ajschumacher/selfcontain/tarball/0.2
Platform: UNKNOWN
